{
  "items": [
    {
      "item": 1,
      "ambito": "Produto",
      "tema": "Jornada de Cliente | Aumento de Capital & Alteração coberturas - PRO RATA",
      "estado": "Business Requirements",
      "team": "CORE",
      "dt_prod": "",
      "dt_train": "",
      "jira": "",
      "change_id": "HELP-22263",
      "notes": [
        {
          "date": "18/05/2026",
          "text": "Sessão interna realizada. Requirements em preparação e avalição de plano de implementação."
        }
      ]
    },
    {
      "item": 11,
      "ambito": "Subscrição",
      "tema": "Alteração Subscrição | QC por Produto",
      "estado": "Business Requirements",
      "team": "CORE/IBG",
      "dt_prod": "",
      "dt_train": "",
      "jira": "",
      "change_id": "HELP-25214",
      "notes": [
        {
          "date": "10/04/2026",
          "text": "MunichRe confirma que podemos enviar coberturas distintas por QC e teremos resposta especifica"
        }
      ]
    },
    {
      "item": 15,
      "ambito": "FH2.0",
      "tema": "Alinhamento dos Ambientes de Teste",
      "estado": "Pending ASP",
      "team": "INFRAS",
      "dt_prod": "30/06/2025",
      "dt_train": "",
      "jira": "GDP-1530",
      "change_id": "",
      "notes": [
        {
          "date": "18/05/2026",
          "text": "DEV AEGON -> TRAIN FH ok e fechado. Aguardamos ainda data para iniciar testes PRE AEGON -> TRAIN FH"
        }
      ]
    },
    {
      "item": 17,
      "ambito": "FH2.0",
      "tema": "Fluxo de Pré-Autorizações e Reembolsos com a Companhia",
      "estado": "QA Approved",
      "team": "CORE",
      "dt_prod": "",
      "dt_train": "04/05/2026",
      "jira": "GDP-1681",
      "change_id": "HELP-22257",
      "notes": [
        {
          "date": "10/05/2026",
          "text": "Aguarda aprovação release QA Global e passagem a Train"
        }
      ]
    },
    {
      "item": 18,
      "ambito": "FH2.0",
      "tema": "Subscrição Clínica - Comunicação com Companhia pelo FHnet",
      "estado": "QA Testing",
      "team": "CORE",
      "dt_prod": "",
      "dt_train": "04/05/2026",
      "jira": "GDP-1749",
      "change_id": "HELP-22371",
      "notes": [
        {
          "date": "24/04/2026",
          "text": "Já está em QA testing. Previsto passagem a Train a 04/05/2026"
        }
      ]
    },
    {
      "item": 19,
      "ambito": "FH2.0",
      "tema": "Valores Acima do Plafond",
      "estado": "Business Requirements",
      "team": "CORE",
      "dt_prod": "",
      "dt_train": "",
      "jira": "GDP-599",
      "change_id": "HELP-22261",
      "notes": [
        {
          "date": "10/05/2026",
          "text": "Iniciamos definição de requisitos. Até dia 14/05/2026 teremos doc requisitos para validação com AEGON"
        }
      ]
    },
    {
      "item": 23,
      "ambito": "FH2.0",
      "tema": "Autorização || Estado FH NET - Histórico de Utilização",
      "estado": "Dev Testing",
      "team": "CORE",
      "dt_prod": "",
      "dt_train": "28/04/2026",
      "jira": "GDP-1962",
      "change_id": "HELP-22268",
      "notes": [
        {
          "date": "17/04/2026",
          "text": "Está em dev testing."
        }
      ]
    },
    {
      "item": 25,
      "ambito": "FH2.0",
      "tema": "Data de Inicio do Risco",
      "estado": "Pending ASP",
      "team": "IBG",
      "dt_prod": "",
      "dt_train": "",
      "jira": "",
      "change_id": "",
      "notes": [
        {
          "date": "10/02/2026",
          "text": "sem qualquer feedback da ASP"
        }
      ]
    },
    {
      "item": 26,
      "ambito": "FH2.0",
      "tema": "Acesso Detalhe da Factura",
      "estado": "QA Testing",
      "team": "CORE",
      "dt_prod": "",
      "dt_train": "04/05/2026",
      "jira": "GDP-1746",
      "change_id": "HELP-22258",
      "notes": [
        {
          "date": "24/04/2026",
          "text": "Já está em QA testing. Previsto passagem a Train a 04/05/2026"
        }
      ]
    },
    {
      "item": 32,
      "ambito": "Área Pessoal",
      "tema": "Timeline de Reembolsos ",
      "estado": "Pending ASP",
      "team": "CORE/CI",
      "dt_prod": "",
      "dt_train": "",
      "jira": "",
      "change_id": "",
      "notes": [
        {
          "date": "09/01/2026",
          "text": "Já está em Produção desde inicio de 12/25 do lado da FH. ASP ainda não se adaptou"
        }
      ]
    },
    {
      "item": 34,
      "ambito": "Área Pessoal",
      "tema": "ONECARE | Autorizações | Informação com detalhe",
      "estado": "Pending ASP",
      "team": "CI",
      "dt_prod": "",
      "dt_train": "",
      "jira": "",
      "change_id": "",
      "notes": [
        {
          "date": "16/06/2025",
          "text": "API FH já suporta e está do lado da ASP efetuar alterações"
        }
      ]
    },
    {
      "item": 36,
      "ambito": "Área Pessoal",
      "tema": "Redes por Produto do Cliente",
      "estado": "Pending ASP",
      "team": "CORE/CI",
      "dt_prod": "",
      "dt_train": "",
      "jira": "",
      "change_id": "",
      "notes": [
        {
          "date": "16/06/2025",
          "text": "API FH já suporta e está do lado da ASP efetuar alterações"
        }
      ]
    },
    {
      "item": 38,
      "ambito": "Área Pessoal",
      "tema": "ONECARE | Reembolsos Filas Submetidos e Criados",
      "estado": "Pending ASP",
      "team": "CORE/CI",
      "dt_prod": "",
      "dt_train": "",
      "jira": "",
      "change_id": "",
      "notes": [
        {
          "date": "09/01/2026",
          "text": "Em Produção desde inicio de Dezembro do lado da FH. ASP ainda não se adaptou"
        }
      ]
    },
    {
      "item": 42,
      "ambito": "Área Pessoal",
      "tema": "ONECARE | Notificações push com alteração de processos (callbacks API)",
      "estado": "Pending ASP",
      "team": "IBG",
      "dt_prod": "",
      "dt_train": "",
      "jira": "GDP-1524",
      "change_id": "",
      "notes": [
        {
          "date": "10/04/2026",
          "text": "Documentação Técnica partilhada com AEGON"
        }
      ]
    },
    {
      "item": 43,
      "ambito": "Sinistros",
      "tema": "Processo de Recuperação da Divida",
      "estado": "In Progress",
      "team": "CORE",
      "dt_prod": "",
      "dt_train": "",
      "jira": "GDP-635",
      "change_id": "",
      "notes": [
        {
          "date": "18/05/2026",
          "text": "Necessário implementar [GE06-12] Odoo Integration - Debt Recovery. Sessão interna com Raquel e Financeira para revisão de prioridade para definir plano de entrega da feature."
        }
      ]
    },
    {
      "item": 55,
      "ambito": "Subscrição",
      "tema": "Melhorias Subscrição ASP - Change Contact Method to Online",
      "estado": "QA Testing",
      "team": "CORE",
      "dt_prod": "",
      "dt_train": "04/05/2026",
      "jira": "GDP-1633",
      "change_id": "HELP-22255",
      "notes": [
        {
          "date": "24/04/2026",
          "text": "Já está em QA testing. Previsto passagem a Train a 04/05/2026"
        }
      ]
    },
    {
      "item": 56,
      "ambito": "Subscrição",
      "tema": "Melhorias Subscrição ASP - SMS Token",
      "estado": "QA Testing",
      "team": "CORE",
      "dt_prod": "",
      "dt_train": "04/05/2026",
      "jira": "GDP-1633",
      "change_id": "HELP-22256",
      "notes": [
        {
          "date": "24/04/2026",
          "text": "Já está em QA testing. Previsto passagem a Train a 04/05/2026"
        }
      ]
    },
    {
      "item": 59,
      "ambito": "Área Pessoal",
      "tema": "API /contract-info/get/contract - add BenefitNumber",
      "estado": "Pending ASP",
      "team": "IBG",
      "dt_prod": "",
      "dt_train": "",
      "jira": "CREQ-136",
      "change_id": "",
      "notes": [
        {
          "date": "24/10/2025",
          "text": "Instalado no dia 23/10 fechado do lado da FH"
        }
      ]
    },
    {
      "item": 62,
      "ambito": "Subscrição",
      "tema": "TUW API Service - add new fields & insured person",
      "estado": "Pending ASP",
      "team": "IBG",
      "dt_prod": "",
      "dt_train": "",
      "jira": "GDP-1667",
      "change_id": "HELP-22267",
      "notes": [
        {
          "date": "24/10/2025",
          "text": "Instalado no dia 23/10. Fechado do lado da FH"
        }
      ]
    },
    {
      "item": 65,
      "ambito": "Projecto Sinistros",
      "tema": "API Get Claims - timeouts - improvements",
      "estado": "Pending ASP",
      "team": "ARCH",
      "dt_prod": "",
      "dt_train": "",
      "jira": "",
      "change_id": "HELP-22450",
      "notes": [
        {
          "date": "29/01/2026",
          "text": "Ainda a aguardar ambient de teste CLEVA/AEGON. AEGON escalou tema internamente para conseguirmos avançar"
        }
      ]
    },
    {
      "item": 67,
      "ambito": "Área Pessoal",
      "tema": "Migração V2 Reembolsos OneCare",
      "estado": "Pending ASP",
      "team": "CI",
      "dt_prod": "",
      "dt_train": "",
      "jira": "",
      "change_id": "",
      "notes": [
        {
          "date": "12/11/2025",
          "text": "Ponto pendente de resposta do OneCare"
        }
      ]
    },
    {
      "item": 68,
      "ambito": "Subscrição",
      "tema": "Histórico de Estados",
      "estado": "In Progress",
      "team": "IBG",
      "dt_prod": "",
      "dt_train": "",
      "jira": "GDP-1966",
      "change_id": "HELP-24759",
      "notes": [
        {
          "date": "10/05/2026",
          "text": "Está em tech review. Aguardamos ok para testes."
        }
      ]
    }
  ],
  "summary": {
    "Business Requirements": 3,
    "Backlog": 16,
    "Closed": 28,
    "Canceled": 2,
    "Pending ASP": 11,
    "QA Approved": 1,
    "QA Testing": 4,
    "Dev Testing": 1,
    "In Progress": 2
  },
  "dateStr": "18 / 05 / 2026",
  "importedFile": "PDS Iniciativas Tecnologia 18052026.xlsx",
  "importedAt": "18/05/2026 às 00:54",
  "execReport": "Overall Status — The portfolio remains healthy with 22 active initiatives and 28 of 68 completed (41%). With 0 items Pending FH and 11 Pending AEGON, the critical path is currently on AEGON's side. The main concern is 7 overdue milestones requiring immediate attention to avoid further slippage.
This Week's Progress —

Closed initiative #16 (Lateralidades nas Exclusões) — moved to Done
Closed initiative #57 (Medical Network Search) — confirmed as service not required
Initiative #1 (Aumento de Capital & Alteração de Coberturas – PRO RATA) advanced from Pending FH to Business Requirements, unblocking design work
Active pipeline holds steady: 4 in QA Testing, 3 in Business Requirements, 2 In Progress, 1 QA Approved, 1 in Dev Testing

Key Actions Required —

Unblock the 11 initiatives currently Pending ASP — these represent the largest queue and are gating downstream delivery
Realign training and production dates for the 7 overdue milestones (#15, #17, #18, #23, #26, #55, #56), with priority on the four with Train dates of 04/05/2026
Confirm new target date for initiative #15 (Alinhamento dos Ambientes de Teste), overdue since 30/06/2025 and a prerequisite for several QA-stage items"
}
